spade_pubsub/__init__.py
spade_pubsub/pubsub.py
spade_pubsub-0.3.0.dist-info/licenses/AUTHORS.rst
spade_pubsub-0.3.0.dist-info/licenses/LICENSE
spade_pubsub-0.3.0.dist-info/METADATA
spade_pubsub-0.3.0.dist-info/WHEEL
spade_pubsub-0.3.0.dist-info/top_level.txt
spade_pubsub-0.3.0.dist-info/RECORD
